payment/__init__.py
payment/__version__.py
payment/azericard.py
payment/goldenpay.py
payment/invoice.py
payment/nestpay.py
payment/utils.py
payment_az-1.1.0.dist-info/METADATA
payment_az-1.1.0.dist-info/WHEEL
payment_az-1.1.0.dist-info/top_level.txt
payment_az-1.1.0.dist-info/RECORD
