Metadata-Version: 2.1
Name: payment-az
Version: 1.1.0
Summary: Django Azerbaycan getewaylari ucun modullar
Home-page: https://github.com/CavidRzayev/payment-az
Author: Cavid Rzayev
Author-email: rzayev592@gmail.com
License: UNKNOWN
Platform: UNKNOWN
Classifier: Programming Language :: Python :: 3
Classifier: License :: OSI Approved :: MIT License
Classifier: Operating System :: OS Independent
Requires-Python: >=3.6
Requires-Dist: requests
Requires-Dist: django
Requires-Dist: aiosmtplib
